gunikite/__init__.py
gunikite/gunicorn_runner.py
gunikite-0.2.0.dist-info/METADATA
gunikite-0.2.0.dist-info/WHEEL
gunikite-0.2.0.dist-info/top_level.txt
gunikite-0.2.0.dist-info/RECORD
