Metadata-Version: 2.1
Name: gunikite
Version: 0.2.0
Summary: Utility for running Gunicorn server from a virtual environment.
Home-page: https://github.com/imamhossainroni/gunikite
Author: Imam Hossain Roni
Author-email: imamhossainroni95@gmail.com
License: MIT
Keywords: gunicorn utility virtual-environment
Classifier: Development Status :: 3 - Alpha
Classifier: Intended Audience :: Developers
Classifier: License :: OSI Approved :: MIT License
Classifier: Programming Language :: Python :: 3
Classifier: Programming Language :: Python :: 3.6
Classifier: Programming Language :: Python :: 3.7
Classifier: Programming Language :: Python :: 3.8
Classifier: Programming Language :: Python :: 3.9
Classifier: Topic :: Software Development :: Libraries :: Python Modules
